{
  "collapse-filter": false,
  "search": "",
  "showTags": true,
  "showAttachments": false,
  "hideUnresolved": false,
  "showOrphans": true,
  "collapse-color-groups": false,
  "colorGroups": [
    {
      "query": "tag:#Attention  ",
      "color": {
        "a": 1,
        "rgb": 14701138
      }
    },
    {
      "query": "tag:#Important  ",
      "color": {
        "a": 1,
        "rgb": 10755519
      }
    }
  ],
  "collapse-display": false,
  "showArrow": false,
  "textFadeMultiplier": 0,
  "nodeSizeMultiplier": 2.00130208333333,
  "lineSizeMultiplier": 1.05703125,
  "collapse-forces": false,
  "centerStrength": 0,
  "repelStrength": 20,
  "linkStrength": 0.497395833333333,
  "linkDistance": 30,
  "scale": 0.030182896283071588,
  "close": true
}